{"01-01":{"holiday":true,"name":"元旦","wage":3,"rest":1},"01-02":{"holiday":true,"name":"元旦","wage":2,"rest":1},"01-21":{"holiday":true,"name":"除夕","wage":3,"rest":2},"01-22":{"holiday":true,"name":"初一","wage":3,"rest":1},"01-23":{"holiday":true,"name":"初二","wage":3,"rest":1},"01-24":{"holiday":true,"name":"初三","wage":3,"rest":1},"01-25":{"holiday":true,"name":"初四","wage":2,"rest":1},"01-26":{"holiday":true,"name":"初五","wage":2,"rest":1},"01-27":{"holiday":true,"name":"初六","wage":2,"rest":1},"01-28":{"holiday":false,"name":"春节后补班","wage":1,"after":true,"target":"春节","rest":1},"01-29":{"holiday":false,"name":"春节后补班","wage":1,"after":true,"target":"春节","rest":1},"04-05":{"holiday":true,"name":"清明节","wage":3,"rest":67},"04-23":{"holiday":false,"name":"劳动节前补班","wage":1,"target":"劳动节","after":false,"rest":1},"04-29":{"holiday":true,"name":"劳动节","wage":2,"rest":7},"04-30":{"holiday":true,"name":"劳动节","wage":2,"rest":1},"05-01":{"holiday":true,"name":"劳动节","wage":3,"rest":1},"05-02":{"holiday":true,"name":"劳动节","wage":3,"rest":1},"05-03":{"holiday":true,"name":"劳动节","wage":3,"rest":1},"05-06":{"holiday":false,"name":"劳动节后补班","after":true,"wage":1,"target":"劳动节","rest":2},"06-22":{"holiday":true,"name":"端午节","wage":3,"rest":2},"06-23":{"holiday":true,"name":"端午节","wage":3,"rest":1},"06-24":{"holiday":true,"name":"端午节","wage":2,"rest":1},"06-25":{"holiday":false,"name":"端午节后补班","wage":1,"target":"端午节","after":true,"rest":1},"09-29":{"holiday":true,"name":"中秋节","wage":3,"rest":83},"09-30":{"holiday":true,"name":"中秋节","wage":3,"rest":1},"10-01":{"holiday":true,"name":"国庆节","wage":3,"rest":1},"10-02":{"holiday":true,"name":"国庆节","wage":3,"rest":1},"10-03":{"holiday":true,"name":"国庆节","wage":2,"rest":1},"10-04":{"holiday":true,"name":"国庆节","wage":2,"rest":1},"10-05":{"holiday":true,"name":"国庆节","wage":2,"rest":1},"10-06":{"holiday":true,"name":"国庆节","wage":2,"rest":1},"10-07":{"holiday":false,"after":true,"wage":1,"name":"国庆节后补班","target":"国庆节","rest":1},"10-08":{"holiday":false,"after":true,"wage":1,"name":"国庆节后补班","target":"国庆节","rest":1},"12-31":{"holiday":true,"name":"元旦","wage":2,"rest":85}}